piat/__init__.py
piat/exceptions.py
piat/parsers/__init__.py
piat/parsers/syslog/__init__.py
piat/parsers/syslog/message.py
piat/parsers/syslog/vendors_descriptors.py
piat/parsers/traps/__init__.py
piat/parsers/traps/trap.py
piat/servers/__init__.py
piat/servers/piat_server.py
piat/servers/syslog_server.py
piat/servers/trap_server.py
piat/utils/__init__.py
piat/utils/decorators.py
piat/utils/logger.py
piat/utils/mib_compiler.py
piat/utils/threads.py
test/__init__.py
test/parsers/__init__.py
test/parsers/syslog/__init__.py
test/parsers/syslog/test_message.py
test/parsers/syslog/test_vendors_descriptors.py
test/parsers/traps/__init__.py
test/parsers/traps/test_trap.py
test/servers/__init__.py
test/servers/test_piat_server.py
test/servers/test_syslog_server.py
test/servers/test_trap_server.py
test/utils/__init__.py
piat-0.0.15.dist-info/LICENSE.txt
piat-0.0.15.dist-info/METADATA
piat-0.0.15.dist-info/WHEEL
piat-0.0.15.dist-info/top_level.txt
piat-0.0.15.dist-info/RECORD
