Metadata-Version: 2.1
Name: piat
Version: 0.0.15
Summary: Syslog and Trap service API
Home-page: https://github.com/Ali-aqrabawi/piat
Author: Ali Aqrabawi
Author-email: aaqrabaw@gmail.com
License: UNKNOWN
Platform: UNKNOWN
Classifier: Development Status :: 4 - Beta
Classifier: Programming Language :: Python :: 3
Classifier: License :: OSI Approved :: MIT License
Classifier: Operating System :: OS Independent
Requires-Dist: pysnmp
